netbox_oxidized/__init__.py
netbox_oxidized/constants.py
netbox_oxidized/fields.py
netbox_oxidized/filters.py
netbox_oxidized/forms.py
netbox_oxidized/models.py
netbox_oxidized/navigation.py
netbox_oxidized/tables.py
netbox_oxidized/template_content.py
netbox_oxidized/urls.py
netbox_oxidized/utils.py
netbox_oxidized/views.py
netbox_oxidized/api/__init__.py
netbox_oxidized/api/serializers.py
netbox_oxidized/api/urls.py
netbox_oxidized/api/views.py
netbox_oxidized/migrations/0001_initial.py
netbox_oxidized/migrations/__init__.py
netbox_oxidized/templates/netbox_oxidized/base_list.html
netbox_oxidized/templates/netbox_oxidized/device_version_list.html
netbox_oxidized/templates/netbox_oxidized/dump_vars.html
netbox_oxidized/templates/netbox_oxidized/import_list.html
netbox_oxidized/templates/netbox_oxidized/import_node_list_old.html
netbox_oxidized/templates/netbox_oxidized/node.html
netbox_oxidized/templates/netbox_oxidized/node_list.html
netbox_oxidized/templates/netbox_oxidized/oxidizednode_edit.html
netbox_oxidized/templates/netbox_oxidized/inc/node_stats.html
netbox_oxidized/templates/netbox_oxidized/inc/version_table.html
netbox_oxidized/templates/netbox_oxidized/widgets/selecttext.html
netbox_oxidized/templatetags/__init__.py
netbox_oxidized/templatetags/plugin_buttons.py
netbox_oxidized/templatetags/plugin_helpers.py
netbox_oxidized-0.3.2.dist-info/LICENSE.txt
netbox_oxidized-0.3.2.dist-info/METADATA
netbox_oxidized-0.3.2.dist-info/NOTICE
netbox_oxidized-0.3.2.dist-info/WHEEL
netbox_oxidized-0.3.2.dist-info/top_level.txt
netbox_oxidized-0.3.2.dist-info/RECORD
