Metadata-Version: 2.1
Name: netbox-oxidized
Version: 0.3.2
Summary: A plugin that integrates oxidized into netbox
Home-page: https://github.com/ragnra/netbox-oxidized
Author: Paul Denning
License: Apache 2.0
Platform: UNKNOWN
Requires-Python: >=3.4
